taxamatcher/__init__.py
taxamatcher/_tm_constants.py
taxamatcher/_tm_main.py
taxamatcher/tm_handler.py
taxamatcher/_jadval/__init__.py
taxamatcher/_jadval/_jadval_adj.py
taxamatcher-1.0.1.data/scripts/taxamatcher
taxamatcher-1.0.1.dist-info/LICENSE
taxamatcher-1.0.1.dist-info/METADATA
taxamatcher-1.0.1.dist-info/WHEEL
taxamatcher-1.0.1.dist-info/top_level.txt
taxamatcher-1.0.1.dist-info/RECORD
