Metadata-Version: 2.1
Name: taxamatcher
Version: 1.0.1
Summary: Easy to use taxonomy correlator
Home-page: https://github.com/mmtechslv/taxamatcher
Author: Farid MUSA
Author-email: farid.musa.h@gmail.com
License: Apache
Keywords: taxonomy taxon taxa lineage taxonomy-assignment greengenes silva taxonomic-classification  bioinformatics metagenomics
Platform: UNKNOWN
Classifier: Development Status :: 5 - Production/Stable
Classifier: Environment :: Console
Classifier: Intended Audience :: Science/Research
Classifier: License :: OSI Approved :: Apache Software License
Classifier: Operating System :: OS Independent
Classifier: Programming Language :: Python :: 3.5
Classifier: Topic :: Scientific/Engineering :: Bio-Informatics
Requires-Dist: click
Requires-Dist: pandas
Requires-Dist: numpy
